global_service/__init__.py
global_service/global_service.py
global_service-0.3.0.dist-info/METADATA
global_service-0.3.0.dist-info/WHEEL
global_service-0.3.0.dist-info/top_level.txt
global_service-0.3.0.dist-info/RECORD
