Metadata-Version: 2.4
Name: global_service
Version: 0.3.0
Summary: Global logging and service utilities for Python projects
Home-page: https://github.com/yourusername/global_service
Author: Rohit Jagatp
Author-email: rohit.jagatp@lighthouseindia.com
License: MIT
Classifier: Programming Language :: Python :: 3
Classifier: License :: OSI Approved :: MIT License
Classifier: Operating System :: OS Independent
Requires-Python: >=3.9
Requires-Dist: requests
Requires-Dist: python-dotenv
Requires-Dist: cx_Oracle
Dynamic: author
Dynamic: author-email
Dynamic: classifier
Dynamic: description
Dynamic: description-content-type
Dynamic: home-page
Dynamic: license
Dynamic: requires-dist
Dynamic: requires-python
Dynamic: summary
